{"ahri":{"wr":51.4,"games":6199},"akali":{"wr":56.45,"games":4496},"akshan":{"wr":52.46,"games":1807},"anivia":{"wr":52.21,"games":1471},"annie":{"wr":51.69,"games":1182},"aurelionsol":{"wr":49.53,"games":739},"aurora":{"wr":52.3,"games":1371},"azir":{"wr":57.6,"games":743},"brand":{"wr":51.77,"games":1781},"cassiopeia":{"wr":52.27,"games":815},"diana":{"wr":53.63,"games":2950},"ekko":{"wr":50.5,"games":2580},"fizz":{"wr":54.64,"games":4870},"galio":{"wr":51.56,"games":2335},"hwei":{"wr":49.35,"games":3094},"irelia":{"wr":51.68,"games":2914},"karma":{"wr":52.1,"games":4681},"kassadin":{"wr":50.68,"games":1679},"katarina":{"wr":52.34,"games":5753},"leblanc":{"wr":55.27,"games":3593},"lux":{"wr":54.08,"games":4325},"malzahar":{"wr":51.91,"games":3275},"mel":{"wr":56.74,"games":2300},"naafiri":{"wr":53.13,"games":5430},"neeko":{"wr":52.95,"games":1135},"orianna":{"wr":54.58,"games":1702},"pantheon":{"wr":55.29,"games":2232},"qiyana":{"wr":53.39,"games":1742},"ryze":{"wr":52.89,"games":1681},"swain":{"wr":54.57,"games":1752},"sylas":{"wr":50.33,"games":5933},"syndra":{"wr":50.07,"games":4911},"taliyah":{"wr":54.23,"games":697},"talon":{"wr":51.07,"games":3313},"twistedfate":{"wr":51.3,"games":2920},"veigar":{"wr":51.7,"games":1849},"vex":{"wr":51.98,"games":1337},"viktor":{"wr":49.36,"games":5162},"vladimir":{"wr":51.08,"games":2837},"xerath":{"wr":49.16,"games":3456},"yasuo":{"wr":57.11,"games":7349},"yone":{"wr":53.32,"games":4734},"zed":{"wr":53.02,"games":6281},"ziggs":{"wr":48.27,"games":2633},"zoe":{"wr":49.2,"games":1502},"locke":{"wr":50,"games":0}}