{"alistar":{"wr":56.99,"games":2032},"bard":{"wr":52.05,"games":3466},"blitzcrank":{"wr":52.57,"games":2431},"brand":{"wr":55.87,"games":979},"braum":{"wr":50.75,"games":1724},"galio":{"wr":54.79,"games":1670},"hwei":{"wr":53.11,"games":1962},"karma":{"wr":53.07,"games":3369},"leona":{"wr":51.61,"games":3889},"lulu":{"wr":51.99,"games":4432},"lux":{"wr":52.97,"games":2426},"maokai":{"wr":51.18,"games":760},"milio":{"wr":51.53,"games":3177},"morgana":{"wr":54.22,"games":1315},"nami":{"wr":52.26,"games":4680},"nautilus":{"wr":52.6,"games":4553},"neeko":{"wr":56.07,"games":758},"poppy":{"wr":54.35,"games":782},"pyke":{"wr":54.24,"games":2994},"rakan":{"wr":51.93,"games":1943},"rell":{"wr":52.46,"games":2154},"renata":{"wr":53.19,"games":564},"senna":{"wr":48.99,"games":3572},"seraphine":{"wr":51.2,"games":4936},"sona":{"wr":49.01,"games":2073},"soraka":{"wr":49.67,"games":2418},"swain":{"wr":57.14,"games":1085},"tahmkench":{"wr":52.45,"games":1060},"taric":{"wr":46.7,"games":651},"thresh":{"wr":49.76,"games":6256},"velkoz":{"wr":54.39,"games":1596},"xerath":{"wr":50.73,"games":1839},"yuumi":{"wr":52.29,"games":2092},"zilean":{"wr":51.2,"games":1664},"zyra":{"wr":53.0,"games":1051}}
