{"ahri":{"wr":45.83,"games":6756},"akali":{"wr":47.14,"games":6160},"akshan":{"wr":47.88,"games":2220},"anivia":{"wr":48.25,"games":1940},"annie":{"wr":46.27,"games":1489},"aurelionsol":{"wr":61.78,"games":1329},"aurora":{"wr":48.34,"games":2019},"azir":{"wr":58.44,"games":1321},"brand":{"wr":51.93,"games":2207},"cassiopeia":{"wr":47.89,"games":1088},"diana":{"wr":48.61,"games":3316},"ekko":{"wr":50.76,"games":2752},"fizz":{"wr":49.99,"games":3475},"galio":{"wr":51.57,"games":4287},"hwei":{"wr":51.43,"games":3315},"irelia":{"wr":49.61,"games":3838},"karma":{"wr":49.5,"games":5697},"kassadin":{"wr":53.42,"games":3426},"katarina":{"wr":48.13,"games":5171},"leblanc":{"wr":48.59,"games":2941},"lissandra":{"wr":46.65,"games":3747},"lux":{"wr":52.71,"games":5526},"malzahar":{"wr":52.88,"games":4026},"mel":{"wr":53.84,"games":2983},"naafiri":{"wr":52.83,"games":6027},"neeko":{"wr":51.99,"games":1381},"orianna":{"wr":54.47,"games":2190},"pantheon":{"wr":47.98,"games":2597},"qiyana":{"wr":52.3,"games":1782},"ryze":{"wr":54.88,"games":2717},"swain":{"wr":53.06,"games":2209},"sylas":{"wr":49.65,"games":7631},"syndra":{"wr":46.6,"games":5290},"taliyah":{"wr":51.85,"games":945},"talon":{"wr":48.61,"games":3458},"twistedfate":{"wr":48.69,"games":3826},"veigar":{"wr":50.02,"games":2085},"vex":{"wr":43.43,"games":2436},"viktor":{"wr":50.55,"games":8048},"vladimir":{"wr":47.46,"games":3647},"xerath":{"wr":51.7,"games":3203},"yasuo":{"wr":55.46,"games":9335},"zed":{"wr":48.43,"games":5207},"ziggs":{"wr":48.9,"games":3544},"zoe":{"wr":49.22,"games":1983},"locke":{"wr":50,"games":0}}