{"mel":{"wr":58.93,"games":582},"naafiri":{"wr":47.96,"games":367},"neeko":{"wr":48.32,"games":298},"orianna":{"wr":59.68,"games":506},"pantheon":{"wr":50.91,"games":605},"qiyana":{"wr":46.54,"games":318},"ryze":{"wr":57.07,"games":552},"swain":{"wr":40.79,"games":152},"sylas":{"wr":50.39,"games":1284},"syndra":{"wr":51.04,"games":1295},"taliyah":{"wr":51.1,"games":182},"talon":{"wr":54.26,"games":258},"twistedfate":{"wr":50.86,"games":875},"veigar":{"wr":52.11,"games":735},"vex":{"wr":50.26,"games":392},"viktor":{"wr":52.88,"games":1477},"vladimir":{"wr":49.51,"games":814},"xerath":{"wr":52.04,"games":736},"yasuo":{"wr":57.59,"games":1337},"yone":{"wr":50.34,"games":872},"zed":{"wr":45.48,"games":919},"ziggs":{"wr":48.44,"games":128},"zoe":{"wr":47.89,"games":380}}
